ipython_beartype/__init__.py
ipython_beartype/py.typed
ipython_beartype-0.2.0.dist-info/METADATA
ipython_beartype-0.2.0.dist-info/WHEEL
ipython_beartype-0.2.0.dist-info/licenses/LICENSE
ipython_beartype-0.2.0.dist-info/RECORD
