Metadata-Version: 2.4
Name: ipython-beartype
Version: 0.2.0
Summary: IPython extension type-checking IPython environments with beartype.
Project-URL: GitHub, https://github.com/beartype/ipython-beartype
Project-URL: Issues, https://github.com/beartype/ipython-beartype/issues
Project-URL: Releases, https://github.com/beartype/ipython-beartype/releases
Author-email: Tushar Sadhwani <tushar.sadhwani000@gmail.com>, Cecil Curry <leycec@gmail.com>
License: MIT License
License-File: LICENSE
Classifier: License :: OSI Approved :: MIT License
Classifier: Operating System :: OS Independent
Classifier: Programming Language :: Python :: 3
Classifier: Programming Language :: Python :: 3 :: Only
Classifier: Programming Language :: Python :: 3.9
Classifier: Programming Language :: Python :: 3.10
Classifier: Programming Language :: Python :: 3.11
Classifier: Programming Language :: Python :: 3.12
Classifier: Programming Language :: Python :: 3.13
Classifier: Programming Language :: Python :: Implementation :: CPython
Classifier: Typing :: Typed
Requires-Python: >=3.9
Requires-Dist: beartype
Requires-Dist: ipython>=8.0.0
Provides-Extra: dev
Requires-Dist: mypy; extra == 'dev'
Requires-Dist: pytest; extra == 'dev'
Requires-Dist: pytest-cov; extra == 'dev'
Requires-Dist: tox; extra == 'dev'
